impgraph/__init__.py
impgraph/__main__.py
impgraph/grapher.py
impgraph/walker.py
impgraph-1.0.0.dist-info/LICENSE
impgraph-1.0.0.dist-info/METADATA
impgraph-1.0.0.dist-info/WHEEL
impgraph-1.0.0.dist-info/entry_points.txt
impgraph-1.0.0.dist-info/top_level.txt
impgraph-1.0.0.dist-info/RECORD
