Metadata-Version: 2.1
Name: impgraph
Version: 1.0.0
Summary: A package for creating import graphs
Home-page: https://github.com/Utkarsh-Patel-13/import-grapher
Author: Utkarsh Patel
Author-email: utkarshhpatel13@gmail.com
License: MIT
Platform: UNKNOWN
Requires-Dist: pygraphviz
Requires-Dist: stdlib-list
Requires-Dist: toml
